lightpads/__init__.py
lightpads/client.py
lightpads-0.0.2.dist-info/licenses/LICENSE
lightpads-0.0.2.dist-info/METADATA
lightpads-0.0.2.dist-info/WHEEL
lightpads-0.0.2.dist-info/top_level.txt
lightpads-0.0.2.dist-info/RECORD
